{
  "artistName": "Tommy Trash",
  "features": [
    {
      "featuredArtist": "Shift K3Y",
      "featuredArtistId": "26OrZl5U3VNGHU9qUj8EcM",
      "trackName": "Luv U Giv - Shift K3Y Remix",
      "trackId": "0UYj2CXIpyh8fspWs177to",
      "preview": "https://p.scdn.co/mp3-preview/471aef65d68cd44f7cf47ffc8c78c59a3cccb64d?cid=9613a0a347504ababc497776c459441f",
      "cover": "https://i.scdn.co/image/e5e67916245fc5af44a32a4828470988b6a7e67e",
      "release_date": "2016-04-08"
    },
    {
      "featuredArtist": "NGHTMRE",
      "featuredArtistId": "76M2Ekj8bG8W7X2nbx2CpF",
      "trackName": "Luv U Giv - NGHTMRE Remix",
      "trackId": "4F9rnOo8ezmG8LcRdGYevt",
      "preview": "https://p.scdn.co/mp3-preview/138c0b3b4fbfd54bd208eb5dbc1e6244b90439d7?cid=9613a0a347504ababc497776c459441f",
      "cover": "https://i.scdn.co/image/e5e67916245fc5af44a32a4828470988b6a7e67e",
      "release_date": "2016-04-08"
    },
    {
      "featuredArtist": "DallasK",
      "featuredArtistId": "7uas0F5EhsZg6KDJ7yy7rW",
      "trackName": "Luv U Giv - DallasK Remix",
      "trackId": "2zmZxZSRneqfaazNrAeRF1",
      "preview": "https://p.scdn.co/mp3-preview/f74282a0220f2c1516fb07c28a0b1be142a74e2d?cid=9613a0a347504ababc497776c459441f",
      "cover": "https://i.scdn.co/image/e5e67916245fc5af44a32a4828470988b6a7e67e",
      "release_date": "2016-04-08"
    },
    {
      "featuredArtist": "Brenmar",
      "featuredArtistId": "713RoDl16muftBPRdCXGAX",
      "trackName": "Body Movin - Brenmar Remix",
      "trackId": "243kCs3Tk3bmlseApfD2SA",
      "preview": "https://p.scdn.co/mp3-preview/54781cf052ca1733e033d04d02aa687a48908c77?cid=9613a0a347504ababc497776c459441f",
      "cover": "https://i.scdn.co/image/e5e67916245fc5af44a32a4828470988b6a7e67e",
      "release_date": "2016-04-08"
    },
    {
      "featuredArtist": "Wax Motif",
      "featuredArtistId": "7zm3aSdmGiOkTt0aZFSO8R",
      "trackName": "Body Movin - Wax Motif Remix",
      "trackId": "2xteiX28AQvXyIA5zaLUZD",
      "preview": "https://p.scdn.co/mp3-preview/2da928b613555ec6bbef0b5d70e88492f3706316?cid=9613a0a347504ababc497776c459441f",
      "cover": "https://i.scdn.co/image/e5e67916245fc5af44a32a4828470988b6a7e67e",
      "release_date": "2016-04-08"
    },
    {
      "featuredArtist": "Anna Lunoe",
      "featuredArtistId": "7d96RW5Vix23AiCHr3mf3D",
      "trackName": "Me & U (feat. Anna Lunoe) - MSCLS Remix",
      "trackId": "2FIQEWQ3YC1PsOH4WAqaCD",
      "preview": "https://p.scdn.co/mp3-preview/abdd684831cb634dd697a2acee1477cf9ba05e60?cid=9613a0a347504ababc497776c459441f",
      "cover": "https://i.scdn.co/image/e5e67916245fc5af44a32a4828470988b6a7e67e",
      "release_date": "2016-04-08"
    },
    {
      "featuredArtist": "MSCLS",
      "featuredArtistId": "4iNrjUgXOTtglPcosEO6A9",
      "trackName": "Me & U (feat. Anna Lunoe) - MSCLS Remix",
      "trackId": "2FIQEWQ3YC1PsOH4WAqaCD",
      "preview": "https://p.scdn.co/mp3-preview/abdd684831cb634dd697a2acee1477cf9ba05e60?cid=9613a0a347504ababc497776c459441f",
      "cover": "https://i.scdn.co/image/e5e67916245fc5af44a32a4828470988b6a7e67e",
      "release_date": "2016-04-08"
    },
    {
      "featuredArtist": "Big Dope P",
      "featuredArtistId": "0eebKLG13kCWzqNI1LItJe",
      "trackName": "Me & U (feat. Anna Lunoe) - Big Dope P & TT The Artist Remix",
      "trackId": "6GgAxTPp4IHgP4YGKL71N6",
      "preview": "https://p.scdn.co/mp3-preview/3c40e59b272ccb084e35ae76242feda4b3dd4ad3?cid=9613a0a347504ababc497776c459441f",
      "cover": "https://i.scdn.co/image/e5e67916245fc5af44a32a4828470988b6a7e67e",
      "release_date": "2016-04-08"
    },
    {
      "featuredArtist": "TT The Artist",
      "featuredArtistId": "1T6Em6UJ7pSdgXw5V72YHr",
      "trackName": "Me & U (feat. Anna Lunoe) - Big Dope P & TT The Artist Remix",
      "trackId": "6GgAxTPp4IHgP4YGKL71N6",
      "preview": "https://p.scdn.co/mp3-preview/3c40e59b272ccb084e35ae76242feda4b3dd4ad3?cid=9613a0a347504ababc497776c459441f",
      "cover": "https://i.scdn.co/image/e5e67916245fc5af44a32a4828470988b6a7e67e",
      "release_date": "2016-04-08"
    },
    {
      "featuredArtist": "Tom Piper",
      "featuredArtistId": "56dC2gUe8pfAWZfPQV5Q8C",
      "trackName": "All My Friends - Radio Edit",
      "trackId": "7x2rORh4TGN0kEXORKhEXX",
      "preview": "https://p.scdn.co/mp3-preview/51b966427439b7ab6c3406cc6a1ab7da48a9de76?cid=9613a0a347504ababc497776c459441f",
      "cover": "https://i.scdn.co/image/6d1a49f5dfd6622c0fd35801abfb184d43a3d420",
      "release_date": "2011-09-23"
    },
    {
      "featuredArtist": "Mr. Wilson",
      "featuredArtistId": "54X7AMGcwAWFpngMGlc2jt",
      "trackName": "All My Friends - Radio Edit",
      "trackId": "7x2rORh4TGN0kEXORKhEXX",
      "preview": "https://p.scdn.co/mp3-preview/51b966427439b7ab6c3406cc6a1ab7da48a9de76?cid=9613a0a347504ababc497776c459441f",
      "cover": "https://i.scdn.co/image/6d1a49f5dfd6622c0fd35801abfb184d43a3d420",
      "release_date": "2011-09-23"
    },
    {
      "featuredArtist": "Neon Stereo",
      "featuredArtistId": "3N4qKgIX0kB0uptMc7mqgG",
      "trackName": "All My Friends - Neon Stereo Remix",
      "trackId": "5OWXAHc6wDdoePeVKCiQyo",
      "preview": "https://p.scdn.co/mp3-preview/07e0cdfc2f8eb891d35b17fcc34c41e4e79d4d52?cid=9613a0a347504ababc497776c459441f",
      "cover": "https://i.scdn.co/image/6d1a49f5dfd6622c0fd35801abfb184d43a3d420",
      "release_date": "2011-09-23"
    },
    {
      "featuredArtist": "Oliver Twizt",
      "featuredArtistId": "4vgjQjCW4yF0dQdfmx2uEs",
      "trackName": "All My Friends - Oliver Twizt Remix",
      "trackId": "0QGEvtG87HgdHbrbSRg3Pu",
      "preview": "https://p.scdn.co/mp3-preview/df06f3ba1646a6d39ce59a92b1faad120dfe7bf9?cid=9613a0a347504ababc497776c459441f",
      "cover": "https://i.scdn.co/image/6d1a49f5dfd6622c0fd35801abfb184d43a3d420",
      "release_date": "2011-09-23"
    },
    {
      "featuredArtist": "MyBack",
      "featuredArtistId": "7tvio9nj5TO7M9g8HBom0o",
      "trackName": "All My Friends - Myback Remix",
      "trackId": "11iD333zXAfr88QtPvruQ8",
      "preview": "https://p.scdn.co/mp3-preview/4f5eb4de5c0a2114b7301df52edae966d411151e?cid=9613a0a347504ababc497776c459441f",
      "cover": "https://i.scdn.co/image/6d1a49f5dfd6622c0fd35801abfb184d43a3d420",
      "release_date": "2011-09-23"
    },
    {
      "featuredArtist": "Piper & Trash",
      "featuredArtistId": "3haxs9vXCAonOGD13kXvEy",
      "trackName": "All My Friends - Piper & Trash Remix",
      "trackId": "45RVEzmrMxDRJ3YdkssSAv",
      "preview": "https://p.scdn.co/mp3-preview/254e6d6069c37a552bf7306453f501097fa5339e?cid=9613a0a347504ababc497776c459441f",
      "cover": "https://i.scdn.co/image/6d1a49f5dfd6622c0fd35801abfb184d43a3d420",
      "release_date": "2011-09-23"
    },
    {
      "featuredArtist": "Carl Kennedy",
      "featuredArtistId": "3db9oGdPmsN2HahMkJCQSs",
      "trackName": "Black Water - Original",
      "trackId": "6F4PiJyImggRBCNy2c9Kjy",
      "preview": "https://p.scdn.co/mp3-preview/62226b8da5eec55639f792adf5ba64807ced3cdb?cid=9613a0a347504ababc497776c459441f",
      "cover": "https://i.scdn.co/image/69999331594e257dc99d3ccf987ecfd243be68f0",
      "release_date": "2011-02-23"
    },
    {
      "featuredArtist": "Rosie Henshaw",
      "featuredArtistId": "0a4sKWPAtv5HAKPAyLhOjn",
      "trackName": "Black Water - Original",
      "trackId": "6F4PiJyImggRBCNy2c9Kjy",
      "preview": "https://p.scdn.co/mp3-preview/62226b8da5eec55639f792adf5ba64807ced3cdb?cid=9613a0a347504ababc497776c459441f",
      "cover": "https://i.scdn.co/image/69999331594e257dc99d3ccf987ecfd243be68f0",
      "release_date": "2011-02-23"
    },
    {
      "featuredArtist": "Timofey & Bartosz Brenes",
      "featuredArtistId": "2x11TxDequN2iJ5BqmFtC2",
      "trackName": "Black Water - Timofey & Bartosz Brenes Mix",
      "trackId": "6lUsnnKLG0qg5BPPYJSxeq",
      "preview": "https://p.scdn.co/mp3-preview/7d8313c44ec48d473d5c894954ff548ad418c7f9?cid=9613a0a347504ababc497776c459441f",
      "cover": "https://i.scdn.co/image/69999331594e257dc99d3ccf987ecfd243be68f0",
      "release_date": "2011-02-23"
    },
    {
      "featuredArtist": "Nyx Syrinx And Nelio",
      "featuredArtistId": "5NmbhOLHwu1w7tfKkgMb4Q",
      "trackName": "Black Water - Nyx Syrinx And Nelio Remix",
      "trackId": "0B9wYs6MsCDh802Vo4j51c",
      "preview": "https://p.scdn.co/mp3-preview/3c951a49dfc4b9645c4678a6819652c1f16b77db?cid=9613a0a347504ababc497776c459441f",
      "cover": "https://i.scdn.co/image/69999331594e257dc99d3ccf987ecfd243be68f0",
      "release_date": "2011-02-23"
    },
    {
      "featuredArtist": "Angger Dimas",
      "featuredArtistId": "5tuOpj3ofDA06hxQjvjdGZ",
      "trackName": "Black Water - Angger Dimas Progressive Remix, Sebastien Lintz Edit",
      "trackId": "6W62qAvWHe4stNJzLvE151",
      "preview": "https://p.scdn.co/mp3-preview/f82541841ec19cc1c460a7f4d6fb7958daf0aa0f?cid=9613a0a347504ababc497776c459441f",
      "cover": "https://i.scdn.co/image/69999331594e257dc99d3ccf987ecfd243be68f0",
      "release_date": "2011-02-23"
    },
    {
      "featuredArtist": "Behrouz",
      "featuredArtistId": "1L6IBprFjkR2f4P1xEBSf7",
      "trackName": "Black Water - Behrouz Ibiza White Island Mix",
      "trackId": "6MlanogNwlTl2GYP1j1fCQ",
      "preview": "https://p.scdn.co/mp3-preview/11af0d8c0ea47be52326000d21fa262ab1b55472?cid=9613a0a347504ababc497776c459441f",
      "cover": "https://i.scdn.co/image/69999331594e257dc99d3ccf987ecfd243be68f0",
      "release_date": "2011-02-23"
    },
    {
      "featuredArtist": "TAISUN",
      "featuredArtistId": "7t8iqCnSCEsqfGDR1sOzDZ",
      "trackName": "IOUE - Horalion Remix",
      "trackId": "07zW1ORYGCkdlLzNGRTwqo",
      "preview": "https://p.scdn.co/mp3-preview/675e704421b529c15db4925c8e39391b1438c16d?cid=9613a0a347504ababc497776c459441f",
      "cover": "https://i.scdn.co/image/4088290a1a87115910e3f46fb6a08f2ba606342c",
      "release_date": "2018-03-19"
    },
    {
      "featuredArtist": "Horalion",
      "featuredArtistId": "2K3O7UPTpvVnW02jj9Jkcs",
      "trackName": "IOUE - Horalion Remix",
      "trackId": "07zW1ORYGCkdlLzNGRTwqo",
      "preview": "https://p.scdn.co/mp3-preview/675e704421b529c15db4925c8e39391b1438c16d?cid=9613a0a347504ababc497776c459441f",
      "cover": "https://i.scdn.co/image/4088290a1a87115910e3f46fb6a08f2ba606342c",
      "release_date": "2018-03-19"
    },
    {
      "featuredArtist": "Mälo",
      "featuredArtistId": "4D22JdgQmFKVKaW0jsTlm8",
      "trackName": "IOUE - Mälo Remix",
      "trackId": "6P31KsrvK9TVI0yngrddiw",
      "preview": "https://p.scdn.co/mp3-preview/c43ea21e513206b5d09728c44500a659ea573921?cid=9613a0a347504ababc497776c459441f",
      "cover": "https://i.scdn.co/image/4088290a1a87115910e3f46fb6a08f2ba606342c",
      "release_date": "2018-03-19"
    },
    {
      "featuredArtist": "djrtnyc",
      "featuredArtistId": "3y0ob0FhA1JqjlptWV8yrD",
      "trackName": "IOUE - djrtnyc Remix",
      "trackId": "58C6SExrp8XTgkNEeHHOb9",
      "preview": "https://p.scdn.co/mp3-preview/bbc836f9b7eafadfb073efae496dc1743aa1780c?cid=9613a0a347504ababc497776c459441f",
      "cover": "https://i.scdn.co/image/4088290a1a87115910e3f46fb6a08f2ba606342c",
      "release_date": "2018-03-19"
    },
    {
      "featuredArtist": "i_o",
      "featuredArtistId": "0y42IQBDFigO5mmEd1bGQG",
      "trackName": "Oxygen (feat. Daisy Guttridge)",
      "trackId": "1tE5h4Vxvz4AFSqedppp3w",
      "preview": "https://p.scdn.co/mp3-preview/077cd2068d1ddeb8afc5f69d453d1af8259cce87?cid=9613a0a347504ababc497776c459441f",
      "cover": "https://i.scdn.co/image/ef6fb776e4355423ff4a1edac054d6a625716ce4",
      "release_date": "2017-12-18"
    },
    {
      "featuredArtist": "Daisy Guttridge",
      "featuredArtistId": "2tUq6RAxkUzZPf2WWLXMa4",
      "trackName": "Oxygen (feat. Daisy Guttridge)",
      "trackId": "1tE5h4Vxvz4AFSqedppp3w",
      "preview": "https://p.scdn.co/mp3-preview/077cd2068d1ddeb8afc5f69d453d1af8259cce87?cid=9613a0a347504ababc497776c459441f",
      "cover": "https://i.scdn.co/image/ef6fb776e4355423ff4a1edac054d6a625716ce4",
      "release_date": "2017-12-18"
    },
    {
      "featuredArtist": "Blanke",
      "featuredArtistId": "59Yq0xrABEihHANsfo9QMT",
      "trackName": "Sinners - Blanke Remix",
      "trackId": "72fOSUxTnppiGYpw4lyHRd",
      "preview": null,
      "cover": "https://i.scdn.co/image/5ce30fa99dfedc940299b019969b522e44a31510",
      "release_date": "2017-10-20"
    },
    {
      "featuredArtist": "DENM",
      "featuredArtistId": "6hrOM3yfx3SEtARzDWMikb",
      "trackName": "Dreamer - Recorded at Spotify Studios NYC",
      "trackId": "6pJVYbB3FlpeqhkGSHnyuo",
      "preview": "https://p.scdn.co/mp3-preview/a75dc582cff1f50c5b988aecd7a5bb1dbd286cef?cid=9613a0a347504ababc497776c459441f",
      "cover": "https://i.scdn.co/image/730ef4233bafa06eb99c6e02200776f28a1bc03d",
      "release_date": "2017-10-18"
    },
    {
      "featuredArtist": "Bryan Grone",
      "featuredArtistId": "11FRez2P2EyaszvkNbsrrn",
      "trackName": "Dreamer - Recorded at Spotify Studios NYC",
      "trackId": "6pJVYbB3FlpeqhkGSHnyuo",
      "preview": "https://p.scdn.co/mp3-preview/a75dc582cff1f50c5b988aecd7a5bb1dbd286cef?cid=9613a0a347504ababc497776c459441f",
      "cover": "https://i.scdn.co/image/730ef4233bafa06eb99c6e02200776f28a1bc03d",
      "release_date": "2017-10-18"
    },
    {
      "featuredArtist": "Death Ray Shake",
      "featuredArtistId": "2BlUAkjOkIi2CVv853XkhA",
      "trackName": "Sinners - Death Ray Shake Remix",
      "trackId": "5qA7ciJFrDG9izJW9fd1VU",
      "preview": null,
      "cover": "https://i.scdn.co/image/729756d26b8eebed4dffc5d00e75c0dd895f1e40",
      "release_date": "2017-10-13"
    },
    {
      "featuredArtist": "Dave Winnel",
      "featuredArtistId": "1K80Wcuuo13i28cVd68mxm",
      "trackName": "Sinners - Dave Winnel Remix",
      "trackId": "1EevgFoazrlaBX9pfmlLHy",
      "preview": null,
      "cover": "https://i.scdn.co/image/729756d26b8eebed4dffc5d00e75c0dd895f1e40",
      "release_date": "2017-10-13"
    },
    {
      "featuredArtist": "Kormak",
      "featuredArtistId": "2bPjd3e5EW7GfP6shz0Py5",
      "trackName": "Sinners - Kormak Remix",
      "trackId": "3uunBIP3R39HnMzMPR5v0c",
      "preview": null,
      "cover": "https://i.scdn.co/image/729756d26b8eebed4dffc5d00e75c0dd895f1e40",
      "release_date": "2017-10-13"
    },
    {
      "featuredArtist": "D.O.D",
      "featuredArtistId": "0Cs47vvRsPgEfliBU9KDiB",
      "trackName": "Don't Wait",
      "trackId": "3UF4od1P3sgqvTI4cTuoZF",
      "preview": "https://p.scdn.co/mp3-preview/ddedf4e979c587e8cffcce27236fca515946df8a?cid=9613a0a347504ababc497776c459441f",
      "cover": "https://i.scdn.co/image/ac0919951510d7f9d240e640f3965a0f4d8df5d5",
      "release_date": "2017-09-11"
    }
  ]
}