{
  "artistName": "Com Truise",
  "features": [
    {
      "featuredArtist": "Joel Ford",
      "featuredArtistId": "5XiDsZ4MdTGfZvUEVBGfiA",
      "trackName": "Declination (feat. Joel Ford)",
      "trackId": "4v33G7cXHGCdUid2FuKOg8",
      "preview": "https://p.scdn.co/mp3-preview/ee2d32850593c229082e02c1e6f3cf1d92f6f1f1?cid=9613a0a347504ababc497776c459441f",
      "cover": "https://i.scdn.co/image/767136be9ce9a3b6f3f01ad563042c5c83a00da2",
      "release_date": "2014-02-17"
    },
    {
      "featuredArtist": "Moodoid",
      "featuredArtistId": "3mQgXwcZz2TZgo9a5diomC",
      "trackName": "Planète Tokyo - Com Truise Remix",
      "trackId": "15LX6DBBlyQvWluFehmWKg",
      "preview": "https://p.scdn.co/mp3-preview/d604b3257122aeeb11ce4dcf13fdb0ada45d8885?cid=9613a0a347504ababc497776c459441f",
      "cover": "https://i.scdn.co/image/abe6cbfde299dd327178047b63f1b23699bfa433",
      "release_date": "2018-03-30"
    },
    {
      "featuredArtist": "Reva DeVito",
      "featuredArtistId": "00jACgDWIBdPM4eH8nORwz",
      "trackName": "BABESQUAD - prod. COM TRUISE",
      "trackId": "13Y9gequ8cDzkpdIQX9XEI",
      "preview": "https://p.scdn.co/mp3-preview/a62c69680b1a00ad8d45783dc60d79fe78be5ca4?cid=9613a0a347504ababc497776c459441f",
      "cover": "https://i.scdn.co/image/65302c2761f3c02260b82b9c326b0ac2a952044d",
      "release_date": "2016-09-30"
    },
    {
      "featuredArtist": "deadmau5",
      "featuredArtistId": "2CIMQHirSU0MQqyYHq0eOx",
      "trackName": "Strobe - Com Truise Remix",
      "trackId": "4NhHZlK1bb5L7Ab9PTe10V",
      "preview": "https://p.scdn.co/mp3-preview/01eb0e5c3f870482ac4f20d16c12716928250e44?cid=9613a0a347504ababc497776c459441f",
      "cover": "https://i.scdn.co/image/bd110da2257ffc812311537c8689b686f63cf71b",
      "release_date": "2016-09-23"
    },
    {
      "featuredArtist": "Deftones",
      "featuredArtistId": "6Ghvu1VvMGScGpOUJBAHNH",
      "trackName": "Prayers / Triangles - Com Truise Remix",
      "trackId": "3AUlTuZMying3mP1ouaDsU",
      "preview": "https://p.scdn.co/mp3-preview/5498c306a336c756d488a0863dc8996e24ea9e62?cid=9613a0a347504ababc497776c459441f",
      "cover": "https://i.scdn.co/image/d7d6eeda205ed07c01ff31c03f6f263811042a6a",
      "release_date": "2016-06-24"
    },
    {
      "featuredArtist": "Midnight To Monaco",
      "featuredArtistId": "3S81oM6w9tzFUxEzvdql6I",
      "trackName": "One in a Million - Com Truise Remix",
      "trackId": "6FMNZwqPXQC0vhOWeCRFAw",
      "preview": "https://p.scdn.co/mp3-preview/7ff8f1e8566be4c9dfc435b9946a5e38d7a496df?cid=9613a0a347504ababc497776c459441f",
      "cover": "https://i.scdn.co/image/a48e64afa51a1741c304dba6b2f4c64f89a0f20d",
      "release_date": "2016-06-10"
    }
  ]
}