{
  "artistName": "Kelly Rowland",
  "features": [
    {
      "featuredArtist": "Wiz Khalifa",
      "featuredArtistId": "137W8MRPWKqSmrBGDBFSop",
      "trackName": "Gone",
      "trackId": "2N3KipO1SUQusJMOWhtL5q",
      "preview": null,
      "cover": "https://i.scdn.co/image/70ee97be514ad9b315118b150cd5f21cf73597b2",
      "release_date": "2013-01-01"
    },
    {
      "featuredArtist": "Kevin Cossom",
      "featuredArtistId": "0Ja9yL6PS5FBnGJimpx504",
      "trackName": "Talk a Good Game",
      "trackId": "3oqGQbesUiyhy2ciZX3HyK",
      "preview": null,
      "cover": "https://i.scdn.co/image/70ee97be514ad9b315118b150cd5f21cf73597b2",
      "release_date": "2013-01-01"
    },
    {
      "featuredArtist": "Beyoncé",
      "featuredArtistId": "6vWDO969PvNqNYHIOW5v0m",
      "trackName": "You Changed",
      "trackId": "0SHNnmeW3a57m3NL0PU5Kp",
      "preview": null,
      "cover": "https://i.scdn.co/image/70ee97be514ad9b315118b150cd5f21cf73597b2",
      "release_date": "2013-01-01"
    },
    {
      "featuredArtist": "Michel'le",
      "featuredArtistId": "4D0WfOUqTzqKysXt33VL3j",
      "trackName": "You Changed",
      "trackId": "0SHNnmeW3a57m3NL0PU5Kp",
      "preview": null,
      "cover": "https://i.scdn.co/image/70ee97be514ad9b315118b150cd5f21cf73597b2",
      "release_date": "2013-01-01"
    },
    {
      "featuredArtist": "Pusha T",
      "featuredArtistId": "0ONHkAv9pCAFxb0zJwDNTy",
      "trackName": "Street Life",
      "trackId": "6eJhYB3WFSFjl8tCRJzfHU",
      "preview": null,
      "cover": "https://i.scdn.co/image/70ee97be514ad9b315118b150cd5f21cf73597b2",
      "release_date": "2013-01-01"
    },
    {
      "featuredArtist": "Michelle",
      "featuredArtistId": "7aJNXzRL7Cac8L6KF7HKUO",
      "trackName": "You Changed",
      "trackId": "1ok1deUBCSftoUEEbLQRnL",
      "preview": null,
      "cover": "https://i.scdn.co/image/3bfc172cd9f729b6dbc6b01a63669ea487466bfd",
      "release_date": "2013-01-01"
    },
    {
      "featuredArtist": "Michelle Williams",
      "featuredArtistId": "6t7nbFAc2dUa7oNu7kBOui",
      "trackName": "You Changed",
      "trackId": "5OL0HH0rTsiJNAMWonCF8F",
      "preview": null,
      "cover": "https://i.scdn.co/image/b0d9d8d3809654b39a5253796d3e4dc9ffd16d8b",
      "release_date": "2013-01-01"
    },
    {
      "featuredArtist": "The Dream",
      "featuredArtistId": "0tdFP7YYasjER1oi3YlRca",
      "trackName": "Sky Walker",
      "trackId": "6S7J8n6vvHzbx8CvGaGRSI",
      "preview": null,
      "cover": "https://i.scdn.co/image/b0d9d8d3809654b39a5253796d3e4dc9ffd16d8b",
      "release_date": "2013-01-01"
    },
    {
      "featuredArtist": "David Guetta",
      "featuredArtistId": "1Cs0zKBU1kc0i8ypK3B9ai",
      "trackName": "When Love Takes Over",
      "trackId": "5qqULE82726KKCplVi4y0c",
      "preview": null,
      "cover": "https://i.scdn.co/image/d111724b4031da8bc312a7fe9b7863780cc08c05",
      "release_date": "2011-10-11"
    },
    {
      "featuredArtist": "Nelly",
      "featuredArtistId": "2gBjLmx6zQnFGQJCAQpRgw",
      "trackName": "Dilemma",
      "trackId": "5okZVbo9rnCtI7IqSj7xwK",
      "preview": null,
      "cover": "https://i.scdn.co/image/d111724b4031da8bc312a7fe9b7863780cc08c05",
      "release_date": "2011-10-11"
    },
    {
      "featuredArtist": "Rob Fusari",
      "featuredArtistId": "5qbs5KV8sxqWfjCs6vmGPG",
      "trackName": "Train On a Track - Rob Fusari Remix",
      "trackId": "0TFhGwVbZnFdxDrq7Fnlgs",
      "preview": "https://p.scdn.co/mp3-preview/ad6356704e2b0c6391da288804d1de13ecf811a3?cid=9613a0a347504ababc497776c459441f",
      "cover": "https://i.scdn.co/image/d111724b4031da8bc312a7fe9b7863780cc08c05",
      "release_date": "2011-10-11"
    },
    {
      "featuredArtist": "Falonte Moore",
      "featuredArtistId": "0y42ZxCGVMSHOl9RFa5NzY",
      "trackName": "Train On a Track - Rob Fusari Remix",
      "trackId": "0TFhGwVbZnFdxDrq7Fnlgs",
      "preview": "https://p.scdn.co/mp3-preview/ad6356704e2b0c6391da288804d1de13ecf811a3?cid=9613a0a347504ababc497776c459441f",
      "cover": "https://i.scdn.co/image/d111724b4031da8bc312a7fe9b7863780cc08c05",
      "release_date": "2011-10-11"
    },
    {
      "featuredArtist": "Tony Bean",
      "featuredArtistId": "3w5qF3v6M92odpSjo1T6Ix",
      "trackName": "Stole - 5am Remix",
      "trackId": "6Ge8Ku9RlyLnMwrsuLoDJ1",
      "preview": "https://p.scdn.co/mp3-preview/2f58c220a5ec186c6e90024725157c6e5b47329f?cid=9613a0a347504ababc497776c459441f",
      "cover": "https://i.scdn.co/image/d111724b4031da8bc312a7fe9b7863780cc08c05",
      "release_date": "2011-10-11"
    },
    {
      "featuredArtist": "Colin Bassett",
      "featuredArtistId": "2WP9POo2dZHn6th1Wo4amp",
      "trackName": "Stole - 5am Remix",
      "trackId": "6Ge8Ku9RlyLnMwrsuLoDJ1",
      "preview": "https://p.scdn.co/mp3-preview/2f58c220a5ec186c6e90024725157c6e5b47329f?cid=9613a0a347504ababc497776c459441f",
      "cover": "https://i.scdn.co/image/d111724b4031da8bc312a7fe9b7863780cc08c05",
      "release_date": "2011-10-11"
    },
    {
      "featuredArtist": "Eve",
      "featuredArtistId": "4d3yvTptO48nOYTPBcPFZC",
      "trackName": "Like This",
      "trackId": "51ann6VymXMHAbZLXCJ74S",
      "preview": "https://p.scdn.co/mp3-preview/6985000fd570d95bf910893617a90ecb1a77294d?cid=9613a0a347504ababc497776c459441f",
      "cover": "https://i.scdn.co/image/d111724b4031da8bc312a7fe9b7863780cc08c05",
      "release_date": "2011-10-11"
    },
    {
      "featuredArtist": "Travis McCoy",
      "featuredArtistId": "46voK5iyMXDdkDpxDgfj2B",
      "trackName": "Daylight",
      "trackId": "6HRatgsE1zXMgiOfJUk9Do",
      "preview": "https://p.scdn.co/mp3-preview/70869e9ea5ee890ac20c4c58724e9c5458fe0c94?cid=9613a0a347504ababc497776c459441f",
      "cover": "https://i.scdn.co/image/d111724b4031da8bc312a7fe9b7863780cc08c05",
      "release_date": "2011-10-11"
    },
    {
      "featuredArtist": "Cedric Solomon for Cedsolo Productions",
      "featuredArtistId": "2H0pTIuebAbnrYwUjxlhr4",
      "trackName": "Can't Nobody - Cedsolo Hip Hop Remix",
      "trackId": "18WbYGWx9O53kC68bwNK6x",
      "preview": "https://p.scdn.co/mp3-preview/76aa7adafbf1b845625957e53cc9957f9ce831d5?cid=9613a0a347504ababc497776c459441f",
      "cover": "https://i.scdn.co/image/d111724b4031da8bc312a7fe9b7863780cc08c05",
      "release_date": "2011-10-11"
    },
    {
      "featuredArtist": "Lil Playy",
      "featuredArtistId": "1d5znoU7LGiCy3H8TMtLWg",
      "trackName": "Work It Man",
      "trackId": "1jvl8eHJq1kFlSjlolVyrV",
      "preview": null,
      "cover": "https://i.scdn.co/image/a8ec69afde3f91a1f93ac3df8f224391facb6d15",
      "release_date": "2011-01-01"
    },
    {
      "featuredArtist": "Lil Wayne",
      "featuredArtistId": "55Aa2cqylxrFIXC767Z865",
      "trackName": "Motivation",
      "trackId": "21Ez4Id4cCDWXC300uAQcz",
      "preview": null,
      "cover": "https://i.scdn.co/image/a8ec69afde3f91a1f93ac3df8f224391facb6d15",
      "release_date": "2011-01-01"
    },
    {
      "featuredArtist": "Big Sean",
      "featuredArtistId": "0c173mlxpT3dSFRgMO8XPh",
      "trackName": "Lay It On Me",
      "trackId": "1G28F4htiHXbVvylNxGNCR",
      "preview": null,
      "cover": "https://i.scdn.co/image/a8ec69afde3f91a1f93ac3df8f224391facb6d15",
      "release_date": "2011-01-01"
    },
    {
      "featuredArtist": "Rico Love",
      "featuredArtistId": "2GEcMpeGIad5O23WxDRFMn",
      "trackName": "All Of The Night",
      "trackId": "1OX4u57feyN99aHXr4sVXN",
      "preview": null,
      "cover": "https://i.scdn.co/image/a8ec69afde3f91a1f93ac3df8f224391facb6d15",
      "release_date": "2011-01-01"
    },
    {
      "featuredArtist": "The WAV.s",
      "featuredArtistId": "4n1jUVWofpK6Lx1r2EnLCo",
      "trackName": "Down For Whatever",
      "trackId": "6XaMJKh56xspZD2CUILDBN",
      "preview": null,
      "cover": "https://i.scdn.co/image/a8ec69afde3f91a1f93ac3df8f224391facb6d15",
      "release_date": "2011-01-01"
    },
    {
      "featuredArtist": "Jim Jonsin",
      "featuredArtistId": "6aWM4NrsAMuOc9uorm6sJ9",
      "trackName": "Motivation - Rebel Rock Remix",
      "trackId": "5MHlBngmmptARFAvJvQscr",
      "preview": null,
      "cover": "https://i.scdn.co/image/a8ec69afde3f91a1f93ac3df8f224391facb6d15",
      "release_date": "2011-01-01"
    },
    {
      "featuredArtist": "Danny Morris",
      "featuredArtistId": "5AW4QiP2Um4dU7KMfZBERf",
      "trackName": "Motivation - Rebel Rock Remix",
      "trackId": "5MHlBngmmptARFAvJvQscr",
      "preview": null,
      "cover": "https://i.scdn.co/image/a8ec69afde3f91a1f93ac3df8f224391facb6d15",
      "release_date": "2011-01-01"
    },
    {
      "featuredArtist": "Alex Gaudino",
      "featuredArtistId": "7vb7VLDqpLTlAy1ctTMR5d",
      "trackName": "What A Feeling - Radio Edit",
      "trackId": "5YvJThYoTv5llA1MQ1g2en",
      "preview": null,
      "cover": "https://i.scdn.co/image/c912e1a713e58099b135646e46a2cec39d30ff63",
      "release_date": "2011-01-01"
    },
    {
      "featuredArtist": "Tank",
      "featuredArtistId": "4mwXUEKaW4ftbncf9Hi58l",
      "trackName": "The Show",
      "trackId": "0ZLIGQ0BYiJhu40aAPl6Od",
      "preview": "https://p.scdn.co/mp3-preview/076e2167648256a64eae69d61f9b8db1f867561d?cid=9613a0a347504ababc497776c459441f",
      "cover": "https://i.scdn.co/image/4004cae607de5695d46a6d7db7c500009623b730",
      "release_date": "2007-07-24"
    },
    {
      "featuredArtist": "Da Brat",
      "featuredArtistId": "2I1bnmb9VQEQGKHxvr0gSf",
      "trackName": "Gotsta Go (Part I) - Radio Edit",
      "trackId": "3QaIIbwbCyq4bD1x3X4pCp",
      "preview": "https://p.scdn.co/mp3-preview/b2cda8e96589d7813a53745044138e5dfc4b1843?cid=9613a0a347504ababc497776c459441f",
      "cover": "https://i.scdn.co/image/d7741d572f497ffd5cc41ecd51b3ecbeddd505b1",
      "release_date": "2007-06-25"
    },
    {
      "featuredArtist": "Amine",
      "featuredArtistId": "3OpXEYnkpqSBaJjFWGeJxy",
      "trackName": "H'bibi I Love You",
      "trackId": "0x3cSq4IQaaVGDgGeMoCK6",
      "preview": "https://p.scdn.co/mp3-preview/283e2dbf53a86f47e84deafa0434a534e3f8cb25?cid=9613a0a347504ababc497776c459441f",
      "cover": "https://i.scdn.co/image/d7741d572f497ffd5cc41ecd51b3ecbeddd505b1",
      "release_date": "2007-06-25"
    }
  ]
}