{
  "artistName": "Skrillex",
  "features": [
    {
      "featuredArtist": "Jack Ü",
      "featuredArtistId": "1HxJeLhIuegM3KgvPn8sTa",
      "trackName": "Don't Do Drugs Just Take Some Jack Ü",
      "trackId": "0iSGRQ1RNaG76qiXH03jyC",
      "preview": "https://p.scdn.co/mp3-preview/295cfda8ae9cefda9f4b8aa23f41288a3f1c7b30?cid=9613a0a347504ababc497776c459441f",
      "cover": "https://i.scdn.co/image/b962d9c0353ef080806b5599cd6618ef0b266880",
      "release_date": "2015-02-24"
    },
    {
      "featuredArtist": "Diplo",
      "featuredArtistId": "5fMUXHkw8R8eOP2RNVYEZX",
      "trackName": "Don't Do Drugs Just Take Some Jack Ü",
      "trackId": "0iSGRQ1RNaG76qiXH03jyC",
      "preview": "https://p.scdn.co/mp3-preview/295cfda8ae9cefda9f4b8aa23f41288a3f1c7b30?cid=9613a0a347504ababc497776c459441f",
      "cover": "https://i.scdn.co/image/b962d9c0353ef080806b5599cd6618ef0b266880",
      "release_date": "2015-02-24"
    },
    {
      "featuredArtist": "Fly Boi Keno",
      "featuredArtistId": "4abEgIF5hnsotmbZleI4Du",
      "trackName": "Beats Knockin (feat. Fly Boi Keno)",
      "trackId": "4gwF1NiLbZl2uKJDS3AX9O",
      "preview": "https://p.scdn.co/mp3-preview/58b8ad9f44115941cfd99d5b591796802ea48479?cid=9613a0a347504ababc497776c459441f",
      "cover": "https://i.scdn.co/image/b962d9c0353ef080806b5599cd6618ef0b266880",
      "release_date": "2015-02-24"
    },
    {
      "featuredArtist": "Kiesza",
      "featuredArtistId": "4zxvC7CRGvggq9EWXOpwAo",
      "trackName": "Take Ü There (feat. Kiesza)",
      "trackId": "2RpKh7kXSdO8NLrW9VQ46p",
      "preview": "https://p.scdn.co/mp3-preview/ddc4594a74270454dd560a522028d54e7f9243a1?cid=9613a0a347504ababc497776c459441f",
      "cover": "https://i.scdn.co/image/b962d9c0353ef080806b5599cd6618ef0b266880",
      "release_date": "2015-02-24"
    },
    {
      "featuredArtist": "2 Chainz",
      "featuredArtistId": "17lzZA2AlOHwCwFALHttmp",
      "trackName": "Febreze (feat. 2 Chainz)",
      "trackId": "48bSfSZaq9Aizbu4AWn4st",
      "preview": "https://p.scdn.co/mp3-preview/b9c9db204b72bd452118d3185df4ad2516faf807?cid=9613a0a347504ababc497776c459441f",
      "cover": "https://i.scdn.co/image/b962d9c0353ef080806b5599cd6618ef0b266880",
      "release_date": "2015-02-24"
    },
    {
      "featuredArtist": "AlunaGeorge",
      "featuredArtistId": "2VAnyOxzJuSAj7XIuEOT38",
      "trackName": "To Ü (feat. AlunaGeorge)",
      "trackId": "3UgSQu6WwrXfKKDq019IHE",
      "preview": "https://p.scdn.co/mp3-preview/1bab97d95d78e1dac17cf93ae528210834c72317?cid=9613a0a347504ababc497776c459441f",
      "cover": "https://i.scdn.co/image/b962d9c0353ef080806b5599cd6618ef0b266880",
      "release_date": "2015-02-24"
    },
    {
      "featuredArtist": "Bunji Garlin",
      "featuredArtistId": "6nPHDCN7qmxO86eN1grP54",
      "trackName": "Jungle Bae (feat. Bunji Garlin & MX Prime)",
      "trackId": "7yJzk64ul9PFgVFUYbEzZL",
      "preview": "https://p.scdn.co/mp3-preview/fc171687ef67c624e3364f4455fd61fad5b7bce9?cid=9613a0a347504ababc497776c459441f",
      "cover": "https://i.scdn.co/image/b962d9c0353ef080806b5599cd6618ef0b266880",
      "release_date": "2015-02-24"
    },
    {
      "featuredArtist": "Mx Prime",
      "featuredArtistId": "6g44ACMA3sXB9D87T6B4yZ",
      "trackName": "Jungle Bae (feat. Bunji Garlin & MX Prime)",
      "trackId": "7yJzk64ul9PFgVFUYbEzZL",
      "preview": "https://p.scdn.co/mp3-preview/fc171687ef67c624e3364f4455fd61fad5b7bce9?cid=9613a0a347504ababc497776c459441f",
      "cover": "https://i.scdn.co/image/b962d9c0353ef080806b5599cd6618ef0b266880",
      "release_date": "2015-02-24"
    },
    {
      "featuredArtist": "Kai",
      "featuredArtistId": "6xHUXzrfhFgnIv86EBR3Ml",
      "trackName": "Mind (feat. Kai)",
      "trackId": "6ZpR2XFuQJSHAQwg9495KZ",
      "preview": "https://p.scdn.co/mp3-preview/15d36f7518607180ba232070151e40ec923a24c6?cid=9613a0a347504ababc497776c459441f",
      "cover": "https://i.scdn.co/image/b962d9c0353ef080806b5599cd6618ef0b266880",
      "release_date": "2015-02-24"
    },
    {
      "featuredArtist": "Snails",
      "featuredArtistId": "2yT7X3Gg2S51DHz67FAYL6",
      "trackName": "Holla Out (feat. Snails & Taranchyla)",
      "trackId": "3LDKrOek8eqZA52IeauhrW",
      "preview": "https://p.scdn.co/mp3-preview/8588ba5e80fcbca6cc660cfb1896b7cffc3b9ae7?cid=9613a0a347504ababc497776c459441f",
      "cover": "https://i.scdn.co/image/b962d9c0353ef080806b5599cd6618ef0b266880",
      "release_date": "2015-02-24"
    },
    {
      "featuredArtist": "Taranchyla",
      "featuredArtistId": "2xSkGZBEbUVJ8z1E0d0pzB",
      "trackName": "Holla Out (feat. Snails & Taranchyla)",
      "trackId": "3LDKrOek8eqZA52IeauhrW",
      "preview": "https://p.scdn.co/mp3-preview/8588ba5e80fcbca6cc660cfb1896b7cffc3b9ae7?cid=9613a0a347504ababc497776c459441f",
      "cover": "https://i.scdn.co/image/b962d9c0353ef080806b5599cd6618ef0b266880",
      "release_date": "2015-02-24"
    },
    {
      "featuredArtist": "Justin Bieber",
      "featuredArtistId": "1uNFoZAHBGtllmzznpCI3s",
      "trackName": "Where Are Ü Now (with Justin Bieber)",
      "trackId": "66hayvUbTotekKU3H4ta1f",
      "preview": "https://p.scdn.co/mp3-preview/edd7282e93a954b2b48cfc136aa63b0396c16406?cid=9613a0a347504ababc497776c459441f",
      "cover": "https://i.scdn.co/image/b962d9c0353ef080806b5599cd6618ef0b266880",
      "release_date": "2015-02-24"
    },
    {
      "featuredArtist": "Missy Elliott",
      "featuredArtistId": "2wIVse2owClT7go1WT98tk",
      "trackName": "Take Ü There (feat. Kiesza) - Missy Elliott Remix Bonus Track",
      "trackId": "4JJTel4WTX7VeyN3fe5CbS",
      "preview": "https://p.scdn.co/mp3-preview/799ae3c76dd0520214e0bfa994850d800adc2c74?cid=9613a0a347504ababc497776c459441f",
      "cover": "https://i.scdn.co/image/b962d9c0353ef080806b5599cd6618ef0b266880",
      "release_date": "2015-02-24"
    },
    {
      "featuredArtist": "pennybirdrabbit",
      "featuredArtistId": "6xDRBrApnv0HI3o6nNl1X3",
      "trackName": "All I Ask Of You (feat. Pennybirdrabbit)",
      "trackId": "0fMAyo16WDEhIGoQHMSFCK",
      "preview": "https://p.scdn.co/mp3-preview/87a48290b3f103f350b865bf94466cce00f98ca4?cid=9613a0a347504ababc497776c459441f",
      "cover": "https://i.scdn.co/image/490a4e8d8fbe39a303b7aec584fd46918b4f0554",
      "release_date": "2010-12-21"
    },
    {
      "featuredArtist": "Bare Noize",
      "featuredArtistId": "1rMry8Rh7VRoaKFWezSaMB",
      "trackName": "Scatta - feat. Foreign Beggars & Bare Noize",
      "trackId": "2l01nCr1aULfmyLs9phUE5",
      "preview": "https://p.scdn.co/mp3-preview/42255ef46802304a8f149c93b10a617daebbe256?cid=9613a0a347504ababc497776c459441f",
      "cover": "https://i.scdn.co/image/490a4e8d8fbe39a303b7aec584fd46918b4f0554",
      "release_date": "2010-12-21"
    },
    {
      "featuredArtist": "Foreign Beggars",
      "featuredArtistId": "0sQ1wgSdRpoysgsa1VnI4G",
      "trackName": "Scatta - feat. Foreign Beggars & Bare Noize",
      "trackId": "2l01nCr1aULfmyLs9phUE5",
      "preview": "https://p.scdn.co/mp3-preview/42255ef46802304a8f149c93b10a617daebbe256?cid=9613a0a347504ababc497776c459441f",
      "cover": "https://i.scdn.co/image/490a4e8d8fbe39a303b7aec584fd46918b4f0554",
      "release_date": "2010-12-21"
    },
    {
      "featuredArtist": "Noisia",
      "featuredArtistId": "4YWj8sohRDjL9deiuRvEEY",
      "trackName": "Scary Monsters And Nice Sprites - Noisia Remix",
      "trackId": "5bPokvOlgW9dRySVnVmyJ9",
      "preview": "https://p.scdn.co/mp3-preview/d2fe8dd097e77c2e0525885f75fbc65574f9fc80?cid=9613a0a347504ababc497776c459441f",
      "cover": "https://i.scdn.co/image/490a4e8d8fbe39a303b7aec584fd46918b4f0554",
      "release_date": "2010-12-21"
    },
    {
      "featuredArtist": "Zedd",
      "featuredArtistId": "2qxJFvFYMEDqd7ui6kSAcq",
      "trackName": "Scary Monsters And Nice Sprites - Zedd Remix",
      "trackId": "1lHtZNCjax5QvCuoluWRuU",
      "preview": "https://p.scdn.co/mp3-preview/77f73597a1ea6900e41ec5938086c3ef7c83993e?cid=9613a0a347504ababc497776c459441f",
      "cover": "https://i.scdn.co/image/490a4e8d8fbe39a303b7aec584fd46918b4f0554",
      "release_date": "2010-12-21"
    },
    {
      "featuredArtist": "Sirah",
      "featuredArtistId": "3oAazIwC0nAYkOKVQPUC38",
      "trackName": "Weekends!!! (feat. Sirah)",
      "trackId": "3Doc0i6JsXK3N1DhhYvmmV",
      "preview": "https://p.scdn.co/mp3-preview/94e329241bd501c1d61f16df56154c5358df943e?cid=9613a0a347504ababc497776c459441f",
      "cover": "https://i.scdn.co/image/490a4e8d8fbe39a303b7aec584fd46918b4f0554",
      "release_date": "2010-12-21"
    },
    {
      "featuredArtist": "What So Not",
      "featuredArtistId": "4AA8eXtzqh5ykxtafLaPOi",
      "trackName": "Goh (feat. KLP)",
      "trackId": "4w7qAiqRPW35J4XrQ7XjWF",
      "preview": "https://p.scdn.co/mp3-preview/870f1f6230857b1f53fcee007c131a1141d9cbeb?cid=9613a0a347504ababc497776c459441f",
      "cover": "https://i.scdn.co/image/925095eb6abd9b886a24a412c86ca77f666ed73d",
      "release_date": "2018-03-08"
    },
    {
      "featuredArtist": "KLP",
      "featuredArtistId": "3cWOwptrfEuGMJ2cM7ipc3",
      "trackName": "Goh (feat. KLP)",
      "trackId": "4w7qAiqRPW35J4XrQ7XjWF",
      "preview": "https://p.scdn.co/mp3-preview/870f1f6230857b1f53fcee007c131a1141d9cbeb?cid=9613a0a347504ababc497776c459441f",
      "cover": "https://i.scdn.co/image/925095eb6abd9b886a24a412c86ca77f666ed73d",
      "release_date": "2018-03-08"
    },
    {
      "featuredArtist": "Kendrick Lamar",
      "featuredArtistId": "2YZyLoL8N0Wb9xBt1NhZWg",
      "trackName": "HUMBLE. - SKRILLEX REMIX",
      "trackId": "65ES1qwOB577ZnTkizMXJJ",
      "preview": null,
      "cover": "https://i.scdn.co/image/30a538ad84f1efa30c5ed1a8113fc18bac3daa9e",
      "release_date": "2017-09-29"
    },
    {
      "featuredArtist": "Poo Bear",
      "featuredArtistId": "3JXpwnHbLvXxY99EuXqFPX",
      "trackName": "Would You Ever - 4B Remix",
      "trackId": "4Vm2CuGPR24AHqrBOAkGdf",
      "preview": "https://p.scdn.co/mp3-preview/cb0e6240a16ecda54baa9a885860bc4272ddafc4?cid=9613a0a347504ababc497776c459441f",
      "cover": "https://i.scdn.co/image/d012c2298246af52676af1ced38dc7ee3f234057",
      "release_date": "2017-09-28"
    },
    {
      "featuredArtist": "4B",
      "featuredArtistId": "0LIl9fjMPEZp8UDiL8Yuo4",
      "trackName": "Would You Ever - 4B Remix",
      "trackId": "4Vm2CuGPR24AHqrBOAkGdf",
      "preview": "https://p.scdn.co/mp3-preview/cb0e6240a16ecda54baa9a885860bc4272ddafc4?cid=9613a0a347504ababc497776c459441f",
      "cover": "https://i.scdn.co/image/d012c2298246af52676af1ced38dc7ee3f234057",
      "release_date": "2017-09-28"
    },
    {
      "featuredArtist": "Branchez",
      "featuredArtistId": "4T5kpUiQUVJhuf9YT28qlf",
      "trackName": "Would You Ever - Branchez & Charlie Klarsfeld Remix",
      "trackId": "7E7oip4ssp3dMHulg1cti2",
      "preview": "https://p.scdn.co/mp3-preview/96f286daaa68a7aa0b70bb34cae0a39291d388f8?cid=9613a0a347504ababc497776c459441f",
      "cover": "https://i.scdn.co/image/16a0592de4195b16218b40734064a26543659a52",
      "release_date": "2017-09-28"
    },
    {
      "featuredArtist": "Charlie Klarsfeld",
      "featuredArtistId": "7IBk1EXqYanGYVIyEdu3SB",
      "trackName": "Would You Ever - Branchez & Charlie Klarsfeld Remix",
      "trackId": "7E7oip4ssp3dMHulg1cti2",
      "preview": "https://p.scdn.co/mp3-preview/96f286daaa68a7aa0b70bb34cae0a39291d388f8?cid=9613a0a347504ababc497776c459441f",
      "cover": "https://i.scdn.co/image/16a0592de4195b16218b40734064a26543659a52",
      "release_date": "2017-09-28"
    },
    {
      "featuredArtist": "Conducta",
      "featuredArtistId": "1lMcg4Y7nW5hHgIVsN9Shn",
      "trackName": "Would You Ever - Conducta Remix",
      "trackId": "1xNh4lhhttDVgXB6qtwzgw",
      "preview": "https://p.scdn.co/mp3-preview/c5d6e8f19ef29744c99887e404726d29ef8b8881?cid=9613a0a347504ababc497776c459441f",
      "cover": "https://i.scdn.co/image/2419b33e3f3934010842cd369a713dae9723dfff",
      "release_date": "2017-09-28"
    },
    {
      "featuredArtist": "Vindata",
      "featuredArtistId": "1Vxf1UfzcxqzqItoOA0DDT",
      "trackName": "Favor",
      "trackId": "6YD9XQ6woFtacq7kPCfEGL",
      "preview": "https://p.scdn.co/mp3-preview/8788ffa51fecc387bc28608347459e4f78c29c96?cid=9613a0a347504ababc497776c459441f",
      "cover": "https://i.scdn.co/image/d26ba96a0db31b0fd0498278215a9e9f201c8ec7",
      "release_date": "2017-08-08"
    },
    {
      "featuredArtist": "NSTASIA",
      "featuredArtistId": "2BBgFkNBBMln3m2G2Bm2bt",
      "trackName": "Favor",
      "trackId": "6YD9XQ6woFtacq7kPCfEGL",
      "preview": "https://p.scdn.co/mp3-preview/8788ffa51fecc387bc28608347459e4f78c29c96?cid=9613a0a347504ababc497776c459441f",
      "cover": "https://i.scdn.co/image/d26ba96a0db31b0fd0498278215a9e9f201c8ec7",
      "release_date": "2017-08-08"
    },
    {
      "featuredArtist": "DJ Sliink",
      "featuredArtistId": "0t9dGS12PMZmiJiZa9vpyk",
      "trackName": "Saint Laurent",
      "trackId": "2AHnUkgAkoOFnkvwRIezrK",
      "preview": "https://p.scdn.co/mp3-preview/eda3618533e5e5f9ed782fd0982da815d01d7c96?cid=9613a0a347504ababc497776c459441f",
      "cover": "https://i.scdn.co/image/2a5f441461034902bdf395619f8aa3c278705afe",
      "release_date": "2017-08-04"
    },
    {
      "featuredArtist": "Wale",
      "featuredArtistId": "67nwj3Y5sZQLl72VNUHEYE",
      "trackName": "Saint Laurent",
      "trackId": "2AHnUkgAkoOFnkvwRIezrK",
      "preview": "https://p.scdn.co/mp3-preview/eda3618533e5e5f9ed782fd0982da815d01d7c96?cid=9613a0a347504ababc497776c459441f",
      "cover": "https://i.scdn.co/image/2a5f441461034902bdf395619f8aa3c278705afe",
      "release_date": "2017-08-04"
    },
    {
      "featuredArtist": "Austin Millz",
      "featuredArtistId": "43UmVQp9qZILibJ5vHq21k",
      "trackName": "Saint Laurent",
      "trackId": "2AHnUkgAkoOFnkvwRIezrK",
      "preview": "https://p.scdn.co/mp3-preview/eda3618533e5e5f9ed782fd0982da815d01d7c96?cid=9613a0a347504ababc497776c459441f",
      "cover": "https://i.scdn.co/image/2a5f441461034902bdf395619f8aa3c278705afe",
      "release_date": "2017-08-04"
    },
    {
      "featuredArtist": "RL Grime",
      "featuredArtistId": "5eIbEEQnDM8yuDVB0bimSP",
      "trackName": "Waiting",
      "trackId": "2TYMKiw4cxosx7TYZZwqVi",
      "preview": "https://p.scdn.co/mp3-preview/fff9aeef60fdcc6801754d0d891d357fa549da9e?cid=9613a0a347504ababc497776c459441f",
      "cover": "https://i.scdn.co/image/777a8b49f54ba76242c4f02e67c6c7453641356b",
      "release_date": "2016-11-03"
    },
    {
      "featuredArtist": "Valentino Khan",
      "featuredArtistId": "0deIjoDjl9g9Zpw0sCIOHh",
      "trackName": "Slam Dunk (feat. Kstylis)",
      "trackId": "2kSijCecfo9ywjCVpaFhcr",
      "preview": "https://p.scdn.co/mp3-preview/19e3c5bc50a803a525970ed9da9ad672d64a15cc?cid=9613a0a347504ababc497776c459441f",
      "cover": "https://i.scdn.co/image/9c9827468fd687d0f69da3036521c84e8f40804a",
      "release_date": "2016-07-29"
    },
    {
      "featuredArtist": "Kstylis",
      "featuredArtistId": "5o2jetVpyIsXvWDT27bN4k",
      "trackName": "Slam Dunk (feat. Kstylis)",
      "trackId": "2kSijCecfo9ywjCVpaFhcr",
      "preview": "https://p.scdn.co/mp3-preview/19e3c5bc50a803a525970ed9da9ad672d64a15cc?cid=9613a0a347504ababc497776c459441f",
      "cover": "https://i.scdn.co/image/9c9827468fd687d0f69da3036521c84e8f40804a",
      "release_date": "2016-07-29"
    },
    {
      "featuredArtist": "Kai",
      "featuredArtistId": "07cXXY7NDK9oWLUvPfUVvx",
      "trackName": "Mind (feat. Kai) - Wiwek Remix",
      "trackId": "1jYmHgepaueEn5peV9MXrY",
      "preview": "https://p.scdn.co/mp3-preview/dd06f688a8bf4d33177df3c6518b41a8c2b7d9ca?cid=9613a0a347504ababc497776c459441f",
      "cover": "https://i.scdn.co/image/cc8acb25c3ef8128d4a3a677aaa302977c525b9d",
      "release_date": "2016-07-28"
    },
    {
      "featuredArtist": "Wiwek",
      "featuredArtistId": "4b2v3PBjJJCF2BX14lIAsT",
      "trackName": "Mind (feat. Kai) - Wiwek Remix",
      "trackId": "1jYmHgepaueEn5peV9MXrY",
      "preview": "https://p.scdn.co/mp3-preview/dd06f688a8bf4d33177df3c6518b41a8c2b7d9ca?cid=9613a0a347504ababc497776c459441f",
      "cover": "https://i.scdn.co/image/cc8acb25c3ef8128d4a3a677aaa302977c525b9d",
      "release_date": "2016-07-28"
    },
    {
      "featuredArtist": "Malaa",
      "featuredArtistId": "7w1eTNePApzDk8XtgykCPS",
      "trackName": "Mind (feat. Kai) - Malaa Remix",
      "trackId": "5zDOFh0uerurV4Bs5uhpiv",
      "preview": "https://p.scdn.co/mp3-preview/9305aa8f5b64d2c3c7893d3a02eefbad8ef20f03?cid=9613a0a347504ababc497776c459441f",
      "cover": "https://i.scdn.co/image/cc8acb25c3ef8128d4a3a677aaa302977c525b9d",
      "release_date": "2016-07-28"
    },
    {
      "featuredArtist": "Ekali",
      "featuredArtistId": "0Y0QSi6lz1bPik5Ffjr8sd",
      "trackName": "Mind (feat. Kai) - Ekali & Gravez Remix",
      "trackId": "6Becybd5TsDaxOiP9YzGf9",
      "preview": "https://p.scdn.co/mp3-preview/19358d37c746f482ace333b684b450046f8224da?cid=9613a0a347504ababc497776c459441f",
      "cover": "https://i.scdn.co/image/cc8acb25c3ef8128d4a3a677aaa302977c525b9d",
      "release_date": "2016-07-28"
    },
    {
      "featuredArtist": "Gravez",
      "featuredArtistId": "2vit5LtsHrU9420Cw4V1jn",
      "trackName": "Mind (feat. Kai) - Ekali & Gravez Remix",
      "trackId": "6Becybd5TsDaxOiP9YzGf9",
      "preview": "https://p.scdn.co/mp3-preview/19358d37c746f482ace333b684b450046f8224da?cid=9613a0a347504ababc497776c459441f",
      "cover": "https://i.scdn.co/image/cc8acb25c3ef8128d4a3a677aaa302977c525b9d",
      "release_date": "2016-07-28"
    },
    {
      "featuredArtist": "BASECAMP",
      "featuredArtistId": "2tT6SE9nGCYXysoJ4qicsZ",
      "trackName": "Mind (feat. Kai) - Basecamp & Mark Johns Remix",
      "trackId": "78IW98YVI8AeRxC38HPuZ4",
      "preview": "https://p.scdn.co/mp3-preview/c25e0387358c05d37416e9d4384ef561e330b61c?cid=9613a0a347504ababc497776c459441f",
      "cover": "https://i.scdn.co/image/cc8acb25c3ef8128d4a3a677aaa302977c525b9d",
      "release_date": "2016-07-28"
    },
    {
      "featuredArtist": "Mark Johns",
      "featuredArtistId": "6zMEGo7y1noMoUEcQfIRCT",
      "trackName": "Mind (feat. Kai) - Basecamp & Mark Johns Remix",
      "trackId": "78IW98YVI8AeRxC38HPuZ4",
      "preview": "https://p.scdn.co/mp3-preview/c25e0387358c05d37416e9d4384ef561e330b61c?cid=9613a0a347504ababc497776c459441f",
      "cover": "https://i.scdn.co/image/cc8acb25c3ef8128d4a3a677aaa302977c525b9d",
      "release_date": "2016-07-28"
    },
    {
      "featuredArtist": "Happy Colors",
      "featuredArtistId": "4nGluPm2aDd2ngK9MkpLp1",
      "trackName": "Mind (feat. Kai) - Happy Colors Remix",
      "trackId": "6jEIPVBL0TLSDQZLbyS51z",
      "preview": "https://p.scdn.co/mp3-preview/a626c56cbc255327e3fc15f151e91ff7b499fc0d?cid=9613a0a347504ababc497776c459441f",
      "cover": "https://i.scdn.co/image/cc8acb25c3ef8128d4a3a677aaa302977c525b9d",
      "release_date": "2016-07-28"
    },
    {
      "featuredArtist": "Oshi",
      "featuredArtistId": "4mAhA39Nr2uEIbQoC3yxOs",
      "trackName": "Mind (feat. Kai) - Oshi Remix",
      "trackId": "3jRbgWVICUA0mikelZh18U",
      "preview": "https://p.scdn.co/mp3-preview/45bb850c45c3416578818ef3e81b526ee95bd9b8?cid=9613a0a347504ababc497776c459441f",
      "cover": "https://i.scdn.co/image/cc8acb25c3ef8128d4a3a677aaa302977c525b9d",
      "release_date": "2016-07-28"
    }
  ]
}