{
  "artistName": "Turma do Pagode",
  "features": [
    {
      "featuredArtist": "Péricles",
      "featuredArtistId": "6oQ4kEIeTHpzOGB5S3r904",
      "trackName": "Mania TDP / Nosso DNA - Ao Vivo",
      "trackId": "0y0C8qRqfrnGgTTPT5sMhg",
      "preview": "https://p.scdn.co/mp3-preview/21bae65f301baf6c5c3a7ccf2dda487cd5ef74e6?cid=9613a0a347504ababc497776c459441f",
      "cover": "https://i.scdn.co/image/aba08dbc36981f430cf5ef47eea116305859b054",
      "release_date": "2017-08-15"
    },
    {
      "featuredArtist": "Chrigor",
      "featuredArtistId": "4FY3d3kLbxwn1NJtdpB4kg",
      "trackName": "Mania TDP / Nosso DNA - Ao Vivo",
      "trackId": "0y0C8qRqfrnGgTTPT5sMhg",
      "preview": "https://p.scdn.co/mp3-preview/21bae65f301baf6c5c3a7ccf2dda487cd5ef74e6?cid=9613a0a347504ababc497776c459441f",
      "cover": "https://i.scdn.co/image/aba08dbc36981f430cf5ef47eea116305859b054",
      "release_date": "2017-08-15"
    },
    {
      "featuredArtist": "Márcio Art",
      "featuredArtistId": "298XMK9Eevpk9rHiGJkXYr",
      "trackName": "Você em Mim / Ôa Ôa - Ao Vivo",
      "trackId": "0MYSxFLcUIqB9E438JLxHU",
      "preview": "https://p.scdn.co/mp3-preview/b88514e0e3da4128298944a3ec4eb51505a729ea?cid=9613a0a347504ababc497776c459441f",
      "cover": "https://i.scdn.co/image/aba08dbc36981f430cf5ef47eea116305859b054",
      "release_date": "2017-08-15"
    },
    {
      "featuredArtist": "Leandro Lehart",
      "featuredArtistId": "5jnbP9Tp4rXCLhYHsDfqtw",
      "trackName": "Você em Mim / Ôa Ôa - Ao Vivo",
      "trackId": "0MYSxFLcUIqB9E438JLxHU",
      "preview": "https://p.scdn.co/mp3-preview/b88514e0e3da4128298944a3ec4eb51505a729ea?cid=9613a0a347504ababc497776c459441f",
      "cover": "https://i.scdn.co/image/aba08dbc36981f430cf5ef47eea116305859b054",
      "release_date": "2017-08-15"
    },
    {
      "featuredArtist": "Dodo",
      "featuredArtistId": "5x0wy0trcqYLvwUG5PFmQL",
      "trackName": "Saudade de Nós / Coisas do Amor (Fã de Carteirinha) - Ao Vivo",
      "trackId": "4kU1Liztvq16IuxgFSSevT",
      "preview": "https://p.scdn.co/mp3-preview/55487f7b439fce4172a50502b78dd670f00e2a05?cid=9613a0a347504ababc497776c459441f",
      "cover": "https://i.scdn.co/image/aba08dbc36981f430cf5ef47eea116305859b054",
      "release_date": "2017-08-15"
    },
    {
      "featuredArtist": "Belo",
      "featuredArtistId": "7hLjkyL9Pz9xtQNahzJZki",
      "trackName": "Não Foi a Tôa / Momentos - Ao Vivo",
      "trackId": "6zmVJUDLyjT58zS7nFwiyo",
      "preview": "https://p.scdn.co/mp3-preview/a1ae26d6c9a4c7593d1c37ef62b65d3a6c5c8761?cid=9613a0a347504ababc497776c459441f",
      "cover": "https://i.scdn.co/image/aba08dbc36981f430cf5ef47eea116305859b054",
      "release_date": "2017-08-15"
    },
    {
      "featuredArtist": "Netinho De Paula",
      "featuredArtistId": "0b2YHyqwdG24iZZEZSagrL",
      "trackName": "Beijo Geladinho / Cohab City - Ao Vivo",
      "trackId": "5OKmnlBQhekcgbvP7w9Oh1",
      "preview": "https://p.scdn.co/mp3-preview/57eac63972db74fa12f1626b55e8a83bd2ad8ab5?cid=9613a0a347504ababc497776c459441f",
      "cover": "https://i.scdn.co/image/aba08dbc36981f430cf5ef47eea116305859b054",
      "release_date": "2017-08-15"
    },
    {
      "featuredArtist": "Reinaldo",
      "featuredArtistId": "3C46KtMg8M2HXzjSWEq2QE",
      "trackName": "Brilho no Olhar / Agora Viu Que Perdeu e Chora / Retrato Cantado de um Amor - Ao Vivo",
      "trackId": "6gpQp1Trz3KKm1WfTgy7z3",
      "preview": "https://p.scdn.co/mp3-preview/27d3324be6bb6f310e8f22f549041a12791b611f?cid=9613a0a347504ababc497776c459441f",
      "cover": "https://i.scdn.co/image/aba08dbc36981f430cf5ef47eea116305859b054",
      "release_date": "2017-08-15"
    },
    {
      "featuredArtist": "Aviões do Forró",
      "featuredArtistId": "4mnhyGRAuExTL4J0soT4za",
      "trackName": "Puxa Agarra e Beija - Ao Vivo",
      "trackId": "4LjpHe6L21jyTIb2CjtSKE",
      "preview": "https://p.scdn.co/mp3-preview/d344881ef691675d7935d9fc0c34d45fc947d41e?cid=9613a0a347504ababc497776c459441f",
      "cover": "https://i.scdn.co/image/6d284995b467fed55e6b93ccfb3d0f19e066be32",
      "release_date": "2016-03-18"
    },
    {
      "featuredArtist": "Thiaguinho",
      "featuredArtistId": "1vppDmG3i5sXf3DJzrK4T1",
      "trackName": "Beija Aqui - Ao Vivo",
      "trackId": "3nvWvHRoqCGsfGLApJtS5M",
      "preview": "https://p.scdn.co/mp3-preview/39484de80aa71b7e5bcada501c136776d069e6c5?cid=9613a0a347504ababc497776c459441f",
      "cover": "https://i.scdn.co/image/6d284995b467fed55e6b93ccfb3d0f19e066be32",
      "release_date": "2016-03-18"
    },
    {
      "featuredArtist": "Arlindo Cruz",
      "featuredArtistId": "096an3uS6ZaK2XySae6SqP",
      "trackName": "Ordem e Progresso - Ao Vivo",
      "trackId": "6g3jkHJoSxYMAvAsC6sY5K",
      "preview": "https://p.scdn.co/mp3-preview/f9a8dda3169d9e63a10d9425140319c79657086b?cid=9613a0a347504ababc497776c459441f",
      "cover": "https://i.scdn.co/image/6d284995b467fed55e6b93ccfb3d0f19e066be32",
      "release_date": "2016-03-18"
    },
    {
      "featuredArtist": "Mumuzinho",
      "featuredArtistId": "34dfPo3Zi55yM6oV46q4y7",
      "trackName": "A Paz Que Faltava - Ao Vivo",
      "trackId": "1bWvszgGdafjv1x3GjTQe8",
      "preview": "https://p.scdn.co/mp3-preview/22f874dc868289169f3e7e6e499a78581b086189?cid=9613a0a347504ababc497776c459441f",
      "cover": "https://i.scdn.co/image/4de15b653425a16799e6bc694d1d501f8ced6ba3",
      "release_date": "2014-04-15"
    },
    {
      "featuredArtist": "Só Pra Contrariar",
      "featuredArtistId": "2B8HcBRTizIsSPryM46Sb1",
      "trackName": "Surreal - Ao Vivo",
      "trackId": "5gECJfxkSJmg6BP0mkViIx",
      "preview": "https://p.scdn.co/mp3-preview/6af8e3521c459c495f3b501115dcf68523cd6cf1?cid=9613a0a347504ababc497776c459441f",
      "cover": "https://i.scdn.co/image/4de15b653425a16799e6bc694d1d501f8ced6ba3",
      "release_date": "2014-04-15"
    },
    {
      "featuredArtist": "Mc Guime",
      "featuredArtistId": "3ge4xOaKvWfhRwgx0Rldov",
      "trackName": "Deu a Louca (Com Rap) - Ao Vivo",
      "trackId": "7oYxisXaak2QAjYC6BRBeH",
      "preview": "https://p.scdn.co/mp3-preview/fac6a4e3f6eff0a4b3210da1a10a8d0f0b76a276?cid=9613a0a347504ababc497776c459441f",
      "cover": "https://i.scdn.co/image/4de15b653425a16799e6bc694d1d501f8ced6ba3",
      "release_date": "2014-04-15"
    },
    {
      "featuredArtist": "Sorriso Maroto",
      "featuredArtistId": "1fUSLFr4WUBx7joEcGwpvG",
      "trackName": "Tá Louco Héin - Ao Vivo",
      "trackId": "5dCsHs5nynTHGdua0raMRR",
      "preview": "https://p.scdn.co/mp3-preview/6a640a76fa96fd6672532d8e25eda2d5bca54f24?cid=9613a0a347504ababc497776c459441f",
      "cover": "https://i.scdn.co/image/4de15b653425a16799e6bc694d1d501f8ced6ba3",
      "release_date": "2014-04-15"
    },
    {
      "featuredArtist": "Péricles",
      "featuredArtistId": "6gEzJZrbm0F4ihvE9iXR9z",
      "trackName": "Esse Adeus",
      "trackId": "4g1LiZJL9JKaB8LjLIFpl4",
      "preview": "https://p.scdn.co/mp3-preview/ba21b6e5e48e43f873322ee6b79cfe8ed20cd937?cid=9613a0a347504ababc497776c459441f",
      "cover": "https://i.scdn.co/image/e4b6df10fc6dea57e1483950ae32ca14872926d2",
      "release_date": "2010-03-01"
    },
    {
      "featuredArtist": "Leci Brandao",
      "featuredArtistId": "5iiQvuDCnlXoK8iAhydW0u",
      "trackName": "Vai Com Deus",
      "trackId": "42kzhBwzUfI66JRNttZPPb",
      "preview": "https://p.scdn.co/mp3-preview/56a2b9de0eb4070e220a0aecf762e100bf599853?cid=9613a0a347504ababc497776c459441f",
      "cover": "https://i.scdn.co/image/e4b6df10fc6dea57e1483950ae32ca14872926d2",
      "release_date": "2010-03-01"
    },
    {
      "featuredArtist": "Chrigor",
      "featuredArtistId": "6J2dPGeS2VqFZrpu7dhdZk",
      "trackName": "Mania TDP / Nosso DNA - Ao Vivo",
      "trackId": "4sdLXjNmMfIvwkOcgSkZwa",
      "preview": "https://p.scdn.co/mp3-preview/8576417fbc6c749c28ee22f24aca824d144a8c5e?cid=9613a0a347504ababc497776c459441f",
      "cover": "https://i.scdn.co/image/c38da0052966c00aa6c7929637c2d3f1fff6615b",
      "release_date": "2017-08-11"
    },
    {
      "featuredArtist": "Samba de Cosme",
      "featuredArtistId": "6xeASKudqBrYQiGP47oWxa",
      "trackName": "Ministério dos Solteiros - Ao Vivo",
      "trackId": "6wYWdV88v2fDZI77OEqGkx",
      "preview": "https://p.scdn.co/mp3-preview/fc416cadae03d9aa776b10988af129cb645f9373?cid=9613a0a347504ababc497776c459441f",
      "cover": "https://i.scdn.co/image/84b60c4cd2131cd485f292c5f4e643b31d6acc58",
      "release_date": "2017-12-01"
    },
    {
      "featuredArtist": "Sem Reznha",
      "featuredArtistId": "1jcSJxePI4nTKpjHrWfBNd",
      "trackName": "Quero Ver Você Fazer",
      "trackId": "5cw00vxFzxDIif92nfg7aS",
      "preview": "https://p.scdn.co/mp3-preview/7e4ab9552af5d0c6010741e565ad8a1c5c76de41?cid=9613a0a347504ababc497776c459441f",
      "cover": "https://i.scdn.co/image/2d8ee96ea3a359b514e09ffb602e974a9e1fe45e",
      "release_date": "2017-10-02"
    },
    {
      "featuredArtist": "Grupo Clareou",
      "featuredArtistId": "0Jpjc7Fc84inIqLhOvBU1Q",
      "trackName": "Vai e Vem - Ao Vivo",
      "trackId": "4a700y4yMLACjtLTVfYpqZ",
      "preview": "https://p.scdn.co/mp3-preview/6855e753d877eded943ad31002fe1f5d5ceae013?cid=9613a0a347504ababc497776c459441f",
      "cover": "https://i.scdn.co/image/96cd4c0529cba2ebe8c72a5b0917a4b3a165592f",
      "release_date": "2017-08-04"
    },
    {
      "featuredArtist": "Ferrugem",
      "featuredArtistId": "1V3oTk90JOZfsEKWy3usea",
      "trackName": "Só Penso no Lar (Final Mix) - Ao Vivo",
      "trackId": "4D6kV9pxM14QZoxtGEFNKO",
      "preview": "https://p.scdn.co/mp3-preview/7a70ab1dacd8f89f68613c184ed1b924f33ffe69?cid=9613a0a347504ababc497776c459441f",
      "cover": "https://i.scdn.co/image/96cd4c0529cba2ebe8c72a5b0917a4b3a165592f",
      "release_date": "2017-08-04"
    },
    {
      "featuredArtist": "Jorge Vercillo",
      "featuredArtistId": "783AF57UpgTN2fditDRFSs",
      "trackName": "Só Penso no Lar (Final Mix) - Ao Vivo",
      "trackId": "4D6kV9pxM14QZoxtGEFNKO",
      "preview": "https://p.scdn.co/mp3-preview/7a70ab1dacd8f89f68613c184ed1b924f33ffe69?cid=9613a0a347504ababc497776c459441f",
      "cover": "https://i.scdn.co/image/96cd4c0529cba2ebe8c72a5b0917a4b3a165592f",
      "release_date": "2017-08-04"
    },
    {
      "featuredArtist": "Belo",
      "featuredArtistId": "6QHNawwwuxTTwgoVadMIKr",
      "trackName": "Samba Prime 2017",
      "trackId": "5QOY9FTwXA6tmmQjsacsVq",
      "preview": "https://p.scdn.co/mp3-preview/f6201da02c67cab1107a40df2e10039c82c3f143?cid=9613a0a347504ababc497776c459441f",
      "cover": "https://i.scdn.co/image/f6a0d38da4b3b6bf346d9a384dc5e9e4379ec03a",
      "release_date": "2017-05-14"
    },
    {
      "featuredArtist": "Rodriguinho",
      "featuredArtistId": "1xKdiuYoOCM2oCMErUjvtq",
      "trackName": "Samba Prime 2017",
      "trackId": "5QOY9FTwXA6tmmQjsacsVq",
      "preview": "https://p.scdn.co/mp3-preview/f6201da02c67cab1107a40df2e10039c82c3f143?cid=9613a0a347504ababc497776c459441f",
      "cover": "https://i.scdn.co/image/f6a0d38da4b3b6bf346d9a384dc5e9e4379ec03a",
      "release_date": "2017-05-14"
    },
    {
      "featuredArtist": "Swig & Simpatia",
      "featuredArtistId": "5I64fM1jehbWnU6xhjvqdq",
      "trackName": "Samba Prime 2017",
      "trackId": "5QOY9FTwXA6tmmQjsacsVq",
      "preview": "https://p.scdn.co/mp3-preview/f6201da02c67cab1107a40df2e10039c82c3f143?cid=9613a0a347504ababc497776c459441f",
      "cover": "https://i.scdn.co/image/f6a0d38da4b3b6bf346d9a384dc5e9e4379ec03a",
      "release_date": "2017-05-14"
    },
    {
      "featuredArtist": "Chininha Principe",
      "featuredArtistId": "6nBgcXO14okWU3sZt5Ubnb",
      "trackName": "Samba Prime 2017",
      "trackId": "5QOY9FTwXA6tmmQjsacsVq",
      "preview": "https://p.scdn.co/mp3-preview/f6201da02c67cab1107a40df2e10039c82c3f143?cid=9613a0a347504ababc497776c459441f",
      "cover": "https://i.scdn.co/image/f6a0d38da4b3b6bf346d9a384dc5e9e4379ec03a",
      "release_date": "2017-05-14"
    },
    {
      "featuredArtist": "Sunga De Pano",
      "featuredArtistId": "3PwAVGPCqepptbCFYCd9qR",
      "trackName": "Samba Prime 2017",
      "trackId": "5QOY9FTwXA6tmmQjsacsVq",
      "preview": "https://p.scdn.co/mp3-preview/f6201da02c67cab1107a40df2e10039c82c3f143?cid=9613a0a347504ababc497776c459441f",
      "cover": "https://i.scdn.co/image/f6a0d38da4b3b6bf346d9a384dc5e9e4379ec03a",
      "release_date": "2017-05-14"
    },
    {
      "featuredArtist": "Rodrigo Marim",
      "featuredArtistId": "4B9t63byisdQLU6zYIID4L",
      "trackName": "Agora É Eu - Ao Vivo",
      "trackId": "19LuTBifpKeGdboHe1g0mq",
      "preview": null,
      "cover": "https://i.scdn.co/image/b682f97045bfe3c17d824366cf0f23a426de608e",
      "release_date": "2017-04-28"
    }
  ]
}