{
  "artistName": "Andy Rivera",
  "features": [
    {
      "featuredArtist": "Feid",
      "featuredArtistId": "2LRoIwlKmHjgvigdNGBHNo",
      "trackName": "Te Necesito",
      "trackId": "3omRmW0Y7jlXIIay8MPdGJ",
      "preview": "https://p.scdn.co/mp3-preview/df18515fdaeaf54e97f0d810f2f2e4a6f997f9b8?cid=9613a0a347504ababc497776c459441f",
      "cover": "https://i.scdn.co/image/1986747f9c188e56027992ab1229ab22acab99c3",
      "release_date": "2016-10-19"
    },
    {
      "featuredArtist": "Pipe Calderón",
      "featuredArtistId": "50TqpjP2iRI4hR1wCfVj3w",
      "trackName": "Si Me Quemo en Tu Piel",
      "trackId": "5eHG8HGRVMJK9nGjrtIPgt",
      "preview": "https://p.scdn.co/mp3-preview/9542d154d4862090273be1396bd26ccc79a3416b?cid=9613a0a347504ababc497776c459441f",
      "cover": "https://i.scdn.co/image/1986747f9c188e56027992ab1229ab22acab99c3",
      "release_date": "2016-10-19"
    },
    {
      "featuredArtist": "Yandar & Yostin",
      "featuredArtistId": "3ptY5WTxu77JpAQQnHyxEl",
      "trackName": "No Lo Notas",
      "trackId": "0vQTyYvBvWHUroylI3g3BY",
      "preview": "https://p.scdn.co/mp3-preview/8a9371eaf700b4cffd1632f1f646d9c321a2200d?cid=9613a0a347504ababc497776c459441f",
      "cover": "https://i.scdn.co/image/381369f1a764b1dbd563e2e88316fc41a4ffce53",
      "release_date": "2018-02-16"
    },
    {
      "featuredArtist": "Reykon",
      "featuredArtistId": "3PAwspMN27PDm81WwXDsMf",
      "trackName": "Delirio",
      "trackId": "78Dqawg9UGWiaXcCeoKiI5",
      "preview": "https://p.scdn.co/mp3-preview/d4345e6206f21b1d17b9fc41aa18edfa3aa66ded?cid=9613a0a347504ababc497776c459441f",
      "cover": "https://i.scdn.co/image/503cc854563cec9ed31514e1a2918182cdcd7446",
      "release_date": "2018-01-27"
    },
    {
      "featuredArtist": "The Rudeboyz",
      "featuredArtistId": "7ciBW1p3KBsYIkFk4UmwS8",
      "trackName": "Delirio",
      "trackId": "78Dqawg9UGWiaXcCeoKiI5",
      "preview": "https://p.scdn.co/mp3-preview/d4345e6206f21b1d17b9fc41aa18edfa3aa66ded?cid=9613a0a347504ababc497776c459441f",
      "cover": "https://i.scdn.co/image/503cc854563cec9ed31514e1a2918182cdcd7446",
      "release_date": "2018-01-27"
    },
    {
      "featuredArtist": "Dayme y El High",
      "featuredArtistId": "4JreHVYyb6GqE2BU03Kx96",
      "trackName": "Vamos a Beber (feat. Ronald El Killa, J King & Maximan & Yomo)",
      "trackId": "0w1Ud9Uh1lqpRGIo56TZuZ",
      "preview": "https://p.scdn.co/mp3-preview/5dc152353f20d0b6c88fd2c53e54616621e2b302?cid=9613a0a347504ababc497776c459441f",
      "cover": "https://i.scdn.co/image/1dfe5bb9aabb3cd86ab5637f4ede21ec8c56fc07",
      "release_date": "2017-12-29"
    },
    {
      "featuredArtist": "Ronald El Killa",
      "featuredArtistId": "2jE5NeCBZpgohvRLtQ6v0O",
      "trackName": "Vamos a Beber (feat. Ronald El Killa, J King & Maximan & Yomo)",
      "trackId": "0w1Ud9Uh1lqpRGIo56TZuZ",
      "preview": "https://p.scdn.co/mp3-preview/5dc152353f20d0b6c88fd2c53e54616621e2b302?cid=9613a0a347504ababc497776c459441f",
      "cover": "https://i.scdn.co/image/1dfe5bb9aabb3cd86ab5637f4ede21ec8c56fc07",
      "release_date": "2017-12-29"
    },
    {
      "featuredArtist": "J-King y Maximan",
      "featuredArtistId": "6UBb8ZUUyarsyod6snflAR",
      "trackName": "Vamos a Beber (feat. Ronald El Killa, J King & Maximan & Yomo)",
      "trackId": "0w1Ud9Uh1lqpRGIo56TZuZ",
      "preview": "https://p.scdn.co/mp3-preview/5dc152353f20d0b6c88fd2c53e54616621e2b302?cid=9613a0a347504ababc497776c459441f",
      "cover": "https://i.scdn.co/image/1dfe5bb9aabb3cd86ab5637f4ede21ec8c56fc07",
      "release_date": "2017-12-29"
    },
    {
      "featuredArtist": "Yomo",
      "featuredArtistId": "4myAXQmMuS1lZe8T6Y7eBg",
      "trackName": "Vamos a Beber (feat. Ronald El Killa, J King & Maximan & Yomo)",
      "trackId": "0w1Ud9Uh1lqpRGIo56TZuZ",
      "preview": "https://p.scdn.co/mp3-preview/5dc152353f20d0b6c88fd2c53e54616621e2b302?cid=9613a0a347504ababc497776c459441f",
      "cover": "https://i.scdn.co/image/1dfe5bb9aabb3cd86ab5637f4ede21ec8c56fc07",
      "release_date": "2017-12-29"
    },
    {
      "featuredArtist": "Joey Montana",
      "featuredArtistId": "3ATyg4fGC9F8trfb0GRWmX",
      "trackName": "Enamorarte (feat. Joey Montana)",
      "trackId": "1c1r1qtK4eB2W61LRylkfx",
      "preview": "https://p.scdn.co/mp3-preview/56e51f93f00219fa72d37ecc7b14009413183ac5?cid=9613a0a347504ababc497776c459441f",
      "cover": "https://i.scdn.co/image/893f0091d47818ba5330d2ae1e9bc4fdbf5336d0",
      "release_date": "2017-12-15"
    },
    {
      "featuredArtist": "MC Davo",
      "featuredArtistId": "3TGeuw7OmACouH5JAKkX7I",
      "trackName": "Tiempo (feat. Mc Davo & Lyan)",
      "trackId": "7FWhplEmpJ9zs7bF0xlioY",
      "preview": "https://p.scdn.co/mp3-preview/1d9db9275d83f400e4c4b4f796b1a1cfc6ee1df6?cid=9613a0a347504ababc497776c459441f",
      "cover": "https://i.scdn.co/image/893f0091d47818ba5330d2ae1e9bc4fdbf5336d0",
      "release_date": "2017-12-15"
    },
    {
      "featuredArtist": "Lyan",
      "featuredArtistId": "2GzKA5uPf3Nef6JjkUNk4H",
      "trackName": "Tiempo (feat. Mc Davo & Lyan)",
      "trackId": "7FWhplEmpJ9zs7bF0xlioY",
      "preview": "https://p.scdn.co/mp3-preview/1d9db9275d83f400e4c4b4f796b1a1cfc6ee1df6?cid=9613a0a347504ababc497776c459441f",
      "cover": "https://i.scdn.co/image/893f0091d47818ba5330d2ae1e9bc4fdbf5336d0",
      "release_date": "2017-12-15"
    },
    {
      "featuredArtist": "Lenny Tavárez",
      "featuredArtistId": "1pQWsZQehhS4wavwh7Fnxd",
      "trackName": "Será? (feat. Lenny Tavarez)",
      "trackId": "4hE5m5IcBTCWQCVQJ7Jj52",
      "preview": "https://p.scdn.co/mp3-preview/77098fcbe4ee7ade4fd83df2330e0495586654ff?cid=9613a0a347504ababc497776c459441f",
      "cover": "https://i.scdn.co/image/893f0091d47818ba5330d2ae1e9bc4fdbf5336d0",
      "release_date": "2017-12-15"
    },
    {
      "featuredArtist": "Gaviria",
      "featuredArtistId": "6oub1Q2hC7ZILcOWWn3Eo9",
      "trackName": "Felicidad (feat. Gaviria)",
      "trackId": "25crfl52Maa0VEHNpPYCci",
      "preview": "https://p.scdn.co/mp3-preview/ee23b10726c0428286a4c61966c38cfc44960637?cid=9613a0a347504ababc497776c459441f",
      "cover": "https://i.scdn.co/image/893f0091d47818ba5330d2ae1e9bc4fdbf5336d0",
      "release_date": "2017-12-15"
    },
    {
      "featuredArtist": "Kenai",
      "featuredArtistId": "1Kxm71m1xyOzD1SMcGF0IH",
      "trackName": "Cibernetica (feat. Yomo)",
      "trackId": "0PFM19DZVaZviLjI9pF7dL",
      "preview": "https://p.scdn.co/mp3-preview/09e5d9ee296abb3a87ec793b30e4558e637d21d5?cid=9613a0a347504ababc497776c459441f",
      "cover": "https://i.scdn.co/image/c007e2e068230d9c0604995a007ad1948f47bcff",
      "release_date": "2017-08-15"
    },
    {
      "featuredArtist": "Jory Boy",
      "featuredArtistId": "5lFhCi03HDneWzvCxGctrT",
      "trackName": "Para la Disco",
      "trackId": "2olTJOuZociSqmikFGaNMf",
      "preview": "https://p.scdn.co/mp3-preview/9b5342cc636e386320b2abdc07871715f84fac73?cid=9613a0a347504ababc497776c459441f",
      "cover": "https://i.scdn.co/image/6573c6edd987f9c20b19466a2e9b6403576bd382",
      "release_date": "2017-07-29"
    },
    {
      "featuredArtist": "Noriel",
      "featuredArtistId": "3RtNN1VnooWEn3KQk03DUL",
      "trackName": "Stripper",
      "trackId": "56XiFTogBykxPUzkIl4cd6",
      "preview": "https://p.scdn.co/mp3-preview/6d0cde5683f3e0250f319b3679bad5d8b146ecae?cid=9613a0a347504ababc497776c459441f",
      "cover": "https://i.scdn.co/image/2bd855f16859ce51fe7a605f4268de164f651d72",
      "release_date": "2017-05-26"
    },
    {
      "featuredArtist": "Justin Quiles",
      "featuredArtistId": "14zUHaJZo1mnYtn6IBRaRP",
      "trackName": "Quédate - Remix",
      "trackId": "5zke2XVsA1jZADDgXtIomh",
      "preview": "https://p.scdn.co/mp3-preview/99c1c3341704bcb431c18c10e9b03ebb4350e5fb?cid=9613a0a347504ababc497776c459441f",
      "cover": "https://i.scdn.co/image/cf589ad58d9a6c8d08963fdc362b67a2937a1ac4",
      "release_date": "2016-09-23"
    },
    {
      "featuredArtist": "Mackie",
      "featuredArtistId": "4LyGCVZ22bGCY4BaW04Uyl",
      "trackName": "Quédate - Remix",
      "trackId": "5zke2XVsA1jZADDgXtIomh",
      "preview": "https://p.scdn.co/mp3-preview/99c1c3341704bcb431c18c10e9b03ebb4350e5fb?cid=9613a0a347504ababc497776c459441f",
      "cover": "https://i.scdn.co/image/cf589ad58d9a6c8d08963fdc362b67a2937a1ac4",
      "release_date": "2016-09-23"
    }
  ]
}