{
  "artistName": "NAV",
  "features": [
    {
      "featuredArtist": "Metro Boomin",
      "featuredArtistId": "0iEtIxbK0KxaSlF7G42ZOp",
      "trackName": "Perfect Timing (Intro)",
      "trackId": "3UFb8JAHt32n86rCYsLYrj",
      "preview": null,
      "cover": "https://i.scdn.co/image/dc4d9da13936c8324c414afa13f78ac266f42831",
      "release_date": "2017-08-04"
    },
    {
      "featuredArtist": "Lil Uzi Vert",
      "featuredArtistId": "4O15NlyKLIASxsJ0PrXPfz",
      "trackName": "A$AP Ferg",
      "trackId": "3YrJZZ93Zs9HfryLXJFwYj",
      "preview": null,
      "cover": "https://i.scdn.co/image/dc4d9da13936c8324c414afa13f78ac266f42831",
      "release_date": "2017-08-04"
    },
    {
      "featuredArtist": "21 Savage",
      "featuredArtistId": "1URnnhqYAYcrqrcwql10ft",
      "trackName": "Both Sides",
      "trackId": "473dIyaFe5PaPB79HbKwHQ",
      "preview": null,
      "cover": "https://i.scdn.co/image/dc4d9da13936c8324c414afa13f78ac266f42831",
      "release_date": "2017-08-04"
    },
    {
      "featuredArtist": "Belly",
      "featuredArtistId": "6RLwxrSq4JygYA8NmF5BVR",
      "trackName": "You Know",
      "trackId": "3RZeUctMKiZlKx2c9qft8G",
      "preview": null,
      "cover": "https://i.scdn.co/image/dc4d9da13936c8324c414afa13f78ac266f42831",
      "release_date": "2017-08-04"
    },
    {
      "featuredArtist": "Gucci Mane",
      "featuredArtistId": "13y7CgLHjMVRMDqxdx0Xdo",
      "trackName": "Need Some",
      "trackId": "08pHncy2VsRmMkivyi9923",
      "preview": null,
      "cover": "https://i.scdn.co/image/dc4d9da13936c8324c414afa13f78ac266f42831",
      "release_date": "2017-08-04"
    },
    {
      "featuredArtist": "Belly",
      "featuredArtistId": "0FOWNUFHPnMy0vOw1siGqi",
      "trackName": "You Know",
      "trackId": "4EWhkuAfQBIPpyMqI97dUB",
      "preview": null,
      "cover": "https://i.scdn.co/image/d9fdb5226c7b210fe965245c0f66692ec6de68ed",
      "release_date": "2017-08-04"
    },
    {
      "featuredArtist": "Playboi Carti",
      "featuredArtistId": "699OTQXzgjhIYAHMy9RyPD",
      "trackName": "Minute",
      "trackId": "2tuPBPax5DPwNAMVbHa4fW",
      "preview": null,
      "cover": "https://i.scdn.co/image/ab59b4f1f2f48db5860b22222c4555ebe6a19d63",
      "release_date": "2017-07-21"
    },
    {
      "featuredArtist": "Offset",
      "featuredArtistId": "4DdkRBBYG6Yk9Ka8tdJ9BW",
      "trackName": "Minute",
      "trackId": "2tuPBPax5DPwNAMVbHa4fW",
      "preview": null,
      "cover": "https://i.scdn.co/image/ab59b4f1f2f48db5860b22222c4555ebe6a19d63",
      "release_date": "2017-07-21"
    },
    {
      "featuredArtist": "The Weeknd",
      "featuredArtistId": "1Xyo4u8uXC1ZmMpatF05PJ",
      "trackName": "Some Way",
      "trackId": "7f2hD8MJRfJI96YfbhIs9b",
      "preview": null,
      "cover": "https://i.scdn.co/image/faadab4a5cebe5ab319820c10c738a25d9b74ae9",
      "release_date": "2017-04-07"
    }
  ]
}